pyjexl/__init__.py
pyjexl/analysis.py
pyjexl/evaluator.py
pyjexl/exceptions.py
pyjexl/jexl.py
pyjexl/operators.py
pyjexl/parser.py
pyjexl-0.3.0.dist-info/LICENSE
pyjexl-0.3.0.dist-info/METADATA
pyjexl-0.3.0.dist-info/WHEEL
pyjexl-0.3.0.dist-info/top_level.txt
pyjexl-0.3.0.dist-info/RECORD
