Metadata-Version: 2.1
Name: pyjexl
Version: 0.3.0
Summary: A JEXL parser and evaluator.
Home-page: https://github.com/Osmose/pyjexl
Author: Osmose (Michael Kelly)
Author-email: me@mkelly.me
License: MIT
Keywords: jexl parser
Platform: UNKNOWN
Classifier: Development Status :: 3 - Alpha
Classifier: Intended Audience :: Developers
Classifier: Topic :: Software Development
Classifier: License :: OSI Approved :: MIT License
Classifier: Programming Language :: Python :: 2.7
Classifier: Programming Language :: Python :: 3.6
License-File: LICENSE
Requires-Dist: parsimonious
Requires-Dist: future
